[
  {
    "symbol": "BTC_USDT",
    "open_interest": 7975920345.52,
    "volume_24h": 4642384320.0
  },
  {
    "symbol": "ETH_USDT",
    "open_interest": 4867999491.92,
    "volume_24h": 9594253938.092392
  },
  {
    "symbol": "SOL_USDT",
    "open_interest": 1085089271.04,
    "volume_24h": 758413326.2367008
  },
  {
    "symbol": "XRP_USDT",
    "open_interest": 903255302.08,
    "volume_24h": 314355664.5188395
  },
  {
    "symbol": "DOGE_USDT",
    "open_interest": 755609095.78,
    "volume_24h": 204219395.6077641
  },
  {
    "symbol": "SOON_USDT",
    "open_interest": 635650415.4,
    "volume_24h": 317103.102420175
  },
  {
    "symbol": "SUI_USDT",
    "open_interest": 285809136.92,
    "volume_24h": 109676247.50342447
  },
  {
    "symbol": "ADA_USDT",
    "open_interest": 235287515.25,
    "volume_24h": 55826288.820257865
  },
  {
    "symbol": "PEPE_USDT",
    "open_interest": 225379210.8,
    "volume_24h": 97601383.24696526
  },
  {
    "symbol": "LINK_USDT",
    "open_interest": 175163484.06,
    "volume_24h": 27809690.985019434
  },
  {
    "symbol": "UNI_USDT",
    "open_interest": 149888133.14,
    "volume_24h": 160642695.59229985
  },
  {
    "symbol": "BNB_USDT",
    "open_interest": 147603683.73,
    "volume_24h": 16863644.48285134
  },
  {
    "symbol": "FIL_USDT",
    "open_interest": 105735471.79,
    "volume_24h": 6769709.842052615
  },
  {
    "symbol": "SHIB_USDT",
    "open_interest": 101235035.61,
    "volume_24h": 6322926.312047857
  },
  {
    "symbol": "TRUMP_USDT",
    "open_interest": 88971411.44,
    "volume_24h": 29732496.857427645
  },
  {
    "symbol": "AVAX_USDT",
    "open_interest": 69748401.48,
    "volume_24h": 28281481.70317932
  },
  {
    "symbol": "LTC_USDT",
    "open_interest": 38068360.03,
    "volume_24h": 204495345.90730634
  },
  {
    "symbol": "BTC_USD",
    "open_interest": 26469416.0,
    "volume_24h": 5526648.0
  },
  {
    "symbol": "TRX_USDT",
    "open_interest": 23881790.17,
    "volume_24h": 31596703.673090167
  },
  {
    "symbol": "FARTCOIN_USDT",
    "open_interest": 19742595.49,
    "volume_24h": 216290932.23650706
  },
  {
    "symbol": "S_USDT",
    "open_interest": 16687471.54,
    "volume_24h": 1321008.969160708
  },
  {
    "symbol": "ENA_USDT",
    "open_interest": 16536038.72,
    "volume_24h": 335263558.2944882
  },
  {
    "symbol": "TON_USDT",
    "open_interest": 15937270.23,
    "volume_24h": 89641090.84089677
  },
  {
    "symbol": "TUT_USDT",
    "open_interest": 14742305.87,
    "volume_24h": 3898566.7222014475
  },
  {
    "symbol": "DOT_USDT",
    "open_interest": 14498417.37,
    "volume_24h": 7089781.6827416355
  },
  {
    "symbol": "BCH_USDT",
    "open_interest": 12139229.42,
    "volume_24h": 97939066.73029009
  },
  {
    "symbol": "ETC_USDT",
    "open_interest": 12066485.46,
    "volume_24h": 41176425.64826901
  },
  {
    "symbol": "ONDO_USDT",
    "open_interest": 11743781.26,
    "volume_24h": 50177450.83971597
  },
  {
    "symbol": "PI_USDT",
    "open_interest": 11228699.76,
    "volume_24h": 75023100.83980377
  },
  {
    "symbol": "ARB_USDT",
    "open_interest": 10554459.4,
    "volume_24h": 7531805.650181417
  },
  {
    "symbol": "WIF_USDT",
    "open_interest": 10268938.77,
    "volume_24h": 70689632.05456099
  },
  {
    "symbol": "KAS_USDT",
    "open_interest": 10078863.9,
    "volume_24h": 37713249.37090826
  },
  {
    "symbol": "TAO_USDT",
    "open_interest": 8797499.68,
    "volume_24h": 14549511.313021135
  },
  {
    "symbol": "APT_USDT",
    "open_interest": 8752202.78,
    "volume_24h": 2415654.252245693
  },
  {
    "symbol": "HBAR_USDT",
    "open_interest": 7949189.7,
    "volume_24h": 72887122.6532805
  },
  {
    "symbol": "GALA_USDT",
    "open_interest": 7774557.85,
    "volume_24h": 20363335.735121604
  },
  {
    "symbol": "AAVE_USDT",
    "open_interest": 7217878.86,
    "volume_24h": 63354942.87501379
  },
  {
    "symbol": "CFX_USDT",
    "open_interest": 7139319.95,
    "volume_24h": 274755529.10882264
  },
  {
    "symbol": "WLD_USDT",
    "open_interest": 7081307.98,
    "volume_24h": 27750463.830888163
  },
  {
    "symbol": "LDO_USDT",
    "open_interest": 6914608.69,
    "volume_24h": 24545983.464690607
  },
  {
    "symbol": "NEAR_USDT",
    "open_interest": 6768047.74,
    "volume_24h": 20709512.011954498
  },
  {
    "symbol": "CRV_USDT",
    "open_interest": 6697809.99,
    "volume_24h": 47020611.70068395
  },
  {
    "symbol": "OP_USDT",
    "open_interest": 6665372.88,
    "volume_24h": 29960178.16609024
  },
  {
    "symbol": "BONK_USDT",
    "open_interest": 6618460.7,
    "volume_24h": 94435945.83688486
  },
  {
    "symbol": "HYPE_USDT",
    "open_interest": 6288129.62,
    "volume_24h": 99861639.94940889
  },
  {
    "symbol": "XLM_USDT",
    "open_interest": 6280192.57,
    "volume_24h": 57633845.341999486
  },
  {
    "symbol": "ORDI_USDT",
    "open_interest": 5915192.9,
    "volume_24h": 3625760.481508061
  },
  {
    "symbol": "AI16Z_USDT",
    "open_interest": 5835003.48,
    "volume_24h": 20289798.944952242
  },
  {
    "symbol": "PENGU_USDT",
    "open_interest": 5567987.67,
    "volume_24h": 254164038.87763396
  },
  {
    "symbol": "PNUT_USDT",
    "open_interest": 4769430.61,
    "volume_24h": 23237070.69399559
  },
  {
    "symbol": "VIRTUAL_USDT",
    "open_interest": 4673999.74,
    "volume_24h": 40357885.45862399
  },
  {
    "symbol": "SPK_USDT",
    "open_interest": 3492517.86,
    "volume_24h": 396552186.49910563
  },
  {
    "symbol": "MAGIC_USDT",
    "open_interest": 3458723.99,
    "volume_24h": 212044983.368941
  },
  {
    "symbol": "INJ_USDT",
    "open_interest": 3446655.13,
    "volume_24h": 45466863.76120454
  },
  {
    "symbol": "TIA_USDT",
    "open_interest": 3366780.32,
    "volume_24h": 7034893.059285678
  },
  {
    "symbol": "MOODENG_USDT",
    "open_interest": 3316646.07,
    "volume_24h": 36093357.445225865
  },
  {
    "symbol": "MORE_USDT",
    "open_interest": 3294326.94,
    "volume_24h": 342914.5925159641
  },
  {
    "symbol": "POPCAT_USDT",
    "open_interest": 3286179.47,
    "volume_24h": 38830784.671983995
  },
  {
    "symbol": "SPX_USDT",
    "open_interest": 3164724.07,
    "volume_24h": 52166140.30118465
  },
  {
    "symbol": "FLOKI_USDT",
    "open_interest": 3157669.59,
    "volume_24h": 22248414.12186139
  },
  {
    "symbol": "M_USDT",
    "open_interest": 3153066.26,
    "volume_24h": 240094090.06049338
  },
  {
    "symbol": "XAUT_USDT",
    "open_interest": 3094135.32,
    "volume_24h": 1080096.745319507
  },
  {
    "symbol": "SEI_USDT",
    "open_interest": 3027709.09,
    "volume_24h": 7541566.868350016
  },
  {
    "symbol": "GT_USDT",
    "open_interest": 2923292.4,
    "volume_24h": 444098.5854933898
  },
  {
    "symbol": "FET_USDT",
    "open_interest": 2914784.6,
    "volume_24h": 2700837.6112921983
  },
  {
    "symbol": "ZORA_USDT",
    "open_interest": 2899392.54,
    "volume_24h": 71454350.07499143
  },
  {
    "symbol": "APE_USDT",
    "open_interest": 2792534.26,
    "volume_24h": 5614444.2252301
  },
  {
    "symbol": "VINE_USDT",
    "open_interest": 2776033.6,
    "volume_24h": 141240697.41657954
  },
  {
    "symbol": "ETHFI_USDT",
    "open_interest": 2706143.03,
    "volume_24h": 20411865.03270152
  },
  {
    "symbol": "ENS_USDT",
    "open_interest": 2678899.65,
    "volume_24h": 3622155.5939547527
  },
  {
    "symbol": "MKR_USDT",
    "open_interest": 2669910.66,
    "volume_24h": 18825851.67672358
  },
  {
    "symbol": "IP_USDT",
    "open_interest": 2648951.42,
    "volume_24h": 32578595.1228218
  },
  {
    "symbol": "OM_USDT",
    "open_interest": 2637294.24,
    "volume_24h": 21368332.37937066
  },
  {
    "symbol": "DYDX_USDT",
    "open_interest": 2585496.47,
    "volume_24h": 2312097.8366112653
  },
  {
    "symbol": "LAUNCHCOIN_USDT",
    "open_interest": 2556912.61,
    "volume_24h": 30360409.794965588
  },
  {
    "symbol": "IKA_USDT",
    "open_interest": 2231538.82,
    "volume_24h": 19484616.48533702
  },
  {
    "symbol": "ATOM_USDT",
    "open_interest": 2143116.35,
    "volume_24h": 2483338.8239464955
  },
  {
    "symbol": "BERA_USDT",
    "open_interest": 2117943.8,
    "volume_24h": 2456509.151111292
  },
  {
    "symbol": "DOG_USDT",
    "open_interest": 2102214.72,
    "volume_24h": 2432119.9167978275
  },
  {
    "symbol": "BSV_USDT",
    "open_interest": 2077359.6,
    "volume_24h": 631506.4135926132
  },
  {
    "symbol": "CAKE_USDT",
    "open_interest": 2028734.25,
    "volume_24h": 3905439.744896623
  },
  {
    "symbol": "EIGEN_USDT",
    "open_interest": 2024146.82,
    "volume_24h": 117973422.25082466
  },
  {
    "symbol": "OMG_USDT",
    "open_interest": 1985216.2,
    "volume_24h": 336889.60614413884
  },
  {
    "symbol": "MASK_USDT",
    "open_interest": 1983266.73,
    "volume_24h": 504869.61125309987
  },
  {
    "symbol": "ICP_USDT",
    "open_interest": 1977330.95,
    "volume_24h": 831078.219653629
  },
  {
    "symbol": "SUSHI_USDT",
    "open_interest": 1867647.6,
    "volume_24h": 2126246.2139085038
  },
  {
    "symbol": "ALCH_USDT",
    "open_interest": 1844772.12,
    "volume_24h": 1317700.1372774523
  },
  {
    "symbol": "SAND_USDT",
    "open_interest": 1734742.68,
    "volume_24h": 818941.1413047398
  },
  {
    "symbol": "BGSC_USDT",
    "open_interest": 1732531.98,
    "volume_24h": 1552800.2916996824
  },
  {
    "symbol": "MOVE_USDT",
    "open_interest": 1693452.22,
    "volume_24h": 879048.5229864144
  },
  {
    "symbol": "RATS_USDT",
    "open_interest": 1666791.98,
    "volume_24h": 738828.8754905284
  },
  {
    "symbol": "AR_USDT",
    "open_interest": 1636830.65,
    "volume_24h": 3489074.2845735317
  },
  {
    "symbol": "ALGO_USDT",
    "open_interest": 1601512.92,
    "volume_24h": 1610174.125840573
  },
  {
    "symbol": "NEWT_USDT",
    "open_interest": 1598965.77,
    "volume_24h": 4478716.844928906
  },
  {
    "symbol": "SOPH_USDT",
    "open_interest": 1584067.21,
    "volume_24h": 41725404.04056669
  },
  {
    "symbol": "STX_USDT",
    "open_interest": 1577510.87,
    "volume_24h": 1839210.9603575391
  },
  {
    "symbol": "PIPPIN_USDT",
    "open_interest": 1568442.81,
    "volume_24h": 3273125.454936426
  },
  {
    "symbol": "A_USDT",
    "open_interest": 1548056.47,
    "volume_24h": 477427.4958482901
  },
  {
    "symbol": "JUP_USDT",
    "open_interest": 1538810.65,
    "volume_24h": 1220106.541895333
  },
  {
    "symbol": "FUN_USDT",
    "open_interest": 1532917.84,
    "volume_24h": 53708571.833799385
  },
  {
    "symbol": "SYRUP_USDT",
    "open_interest": 1525059.25,
    "volume_24h": 29728289.709371854
  },
  {
    "symbol": "HYPER_USDT",
    "open_interest": 1512348.7,
    "volume_24h": 27082377.7881634
  },
  {
    "symbol": "RENDER_USDT",
    "open_interest": 1502252.35,
    "volume_24h": 1867406.6789417195
  },
  {
    "symbol": "TRB_USDT",
    "open_interest": 1484575.46,
    "volume_24h": 1274026.5888152532
  },
  {
    "symbol": "TURBO_USDT",
    "open_interest": 1463391.67,
    "volume_24h": 2054157.8246020696
  },
  {
    "symbol": "POL_USDT",
    "open_interest": 1446341.28,
    "volume_24h": 1173612.6896524094
  },
  {
    "symbol": "BOME_USDT",
    "open_interest": 1411011.96,
    "volume_24h": 935813.6683767476
  },
  {
    "symbol": "GOAT_USDT",
    "open_interest": 1393984.68,
    "volume_24h": 14022195.870995598
  },
  {
    "symbol": "CROSS_USDT",
    "open_interest": 1391399.43,
    "volume_24h": 27910742.30851273
  },
  {
    "symbol": "OMNI_USDT",
    "open_interest": 1352809.5,
    "volume_24h": 29397484.445566572
  },
  {
    "symbol": "ERA_USDT",
    "open_interest": 1343817.57,
    "volume_24h": 77395977.28492191
  },
  {
    "symbol": "SAHARA_USDT",
    "open_interest": 1306905.1,
    "volume_24h": 28849951.240320757
  },
  {
    "symbol": "PEOPLE_USDT",
    "open_interest": 1297747.95,
    "volume_24h": 2014889.7237092368
  },
  {
    "symbol": "GRASS_USDT",
    "open_interest": 1275359.35,
    "volume_24h": 25411361.269914486
  },
  {
    "symbol": "RUNE_USDT",
    "open_interest": 1267691.27,
    "volume_24h": 331902.30046633736
  },
  {
    "symbol": "NEIROETH_USDT",
    "open_interest": 1235222.39,
    "volume_24h": 7496193.274907391
  },
  {
    "symbol": "USDC_USDT",
    "open_interest": 1222684.18,
    "volume_24h": 304866.01860816014
  },
  {
    "symbol": "ZBCN_USDT",
    "open_interest": 1204063.18,
    "volume_24h": 4553501.805127843
  },
  {
    "symbol": "RESOLV_USDT",
    "open_interest": 1194831.77,
    "volume_24h": 2645668.607244013
  },
  {
    "symbol": "TSTBSC_USDT",
    "open_interest": 1190828.13,
    "volume_24h": 1698669.0571646139
  },
  {
    "symbol": "ALEO_USDT",
    "open_interest": 1190211.68,
    "volume_24h": 964233.3213636067
  },
  {
    "symbol": "PENDLE_USDT",
    "open_interest": 1175814.67,
    "volume_24h": 3262927.3664939604
  },
  {
    "symbol": "CRO_USDT",
    "open_interest": 1172960.4,
    "volume_24h": 2788588.7472373396
  },
  {
    "symbol": "TREE_USDT",
    "open_interest": 1145336.9,
    "volume_24h": 19729900.070594672
  },
  {
    "symbol": "KAIA_USDT",
    "open_interest": 1137095.46,
    "volume_24h": 598788.6198296862
  },
  {
    "symbol": "MUBARAK_USDT",
    "open_interest": 1111164.36,
    "volume_24h": 1238203.478420875
  },
  {
    "symbol": "ATH_USDT",
    "open_interest": 1107075.44,
    "volume_24h": 2624752.786001601
  },
  {
    "symbol": "ZK_USDT",
    "open_interest": 1095053.48,
    "volume_24h": 1582162.7536468112
  },
  {
    "symbol": "JTO_USDT",
    "open_interest": 1070349.56,
    "volume_24h": 495488.79866909445
  },
  {
    "symbol": "SWARMS_USDT",
    "open_interest": 1061073.59,
    "volume_24h": 1259820.8637379266
  },
  {
    "symbol": "FORM_USDT",
    "open_interest": 1060044.3,
    "volume_24h": 1564040.0592640298
  },
  {
    "symbol": "B_USDT",
    "open_interest": 1055503.96,
    "volume_24h": 882207.7408054196
  },
  {
    "symbol": "KAITO_USDT",
    "open_interest": 1038538.34,
    "volume_24h": 1322845.9976283472
  },
  {
    "symbol": "COOKIE_USDT",
    "open_interest": 1028725.52,
    "volume_24h": 15354560.163796442
  },
  {
    "symbol": "ME_USDT",
    "open_interest": 1027052.55,
    "volume_24h": 4241147.242398739
  },
  {
    "symbol": "H_USDT",
    "open_interest": 1025698.35,
    "volume_24h": 42871339.259744376
  },
  {
    "symbol": "COMP_USDT",
    "open_interest": 1006802.81,
    "volume_24h": 452236.00194057036
  },
  {
    "symbol": "PUMP_USDT",
    "open_interest": 1003352.68,
    "volume_24h": 204396928.76586378
  },
  {
    "symbol": "WEMIX_USDT",
    "open_interest": 992933.31,
    "volume_24h": 270026.8700788008
  },
  {
    "symbol": "SATS_USDT",
    "open_interest": 991926.53,
    "volume_24h": 395280.010928983
  },
  {
    "symbol": "PAXG_USDT",
    "open_interest": 972977.17,
    "volume_24h": 1655613.1424539299
  },
  {
    "symbol": "PARTI_USDT",
    "open_interest": 967903.65,
    "volume_24h": 4156553.7142250724
  },
  {
    "symbol": "LPT_USDT",
    "open_interest": 957373.78,
    "volume_24h": 2865093.118565345
  },
  {
    "symbol": "STRK_USDT",
    "open_interest": 956554.76,
    "volume_24h": 588657.8518279637
  },
  {
    "symbol": "USUAL_USDT",
    "open_interest": 951861.8,
    "volume_24h": 4699335.107550744
  },
  {
    "symbol": "KERNEL_USDT",
    "open_interest": 947699.24,
    "volume_24h": 5218254.740850635
  },
  {
    "symbol": "XTZ_USDT",
    "open_interest": 934167.89,
    "volume_24h": 2013356.4766052738
  },
  {
    "symbol": "ZEREBRO_USDT",
    "open_interest": 932587.73,
    "volume_24h": 2414323.77160132
  },
  {
    "symbol": "BIO_USDT",
    "open_interest": 923750.68,
    "volume_24h": 15178565.928531824
  },
  {
    "symbol": "MELANIA_USDT",
    "open_interest": 918258.23,
    "volume_24h": 2043622.015599003
  },
  {
    "symbol": "SWELL_USDT",
    "open_interest": 911742.23,
    "volume_24h": 3962562.6624286375
  },
  {
    "symbol": "BRETT_USDT",
    "open_interest": 887841.54,
    "volume_24h": 5561069.054550718
  },
  {
    "symbol": "WCT_USDT",
    "open_interest": 886281.84,
    "volume_24h": 1279614.16299627
  },
  {
    "symbol": "ETHW_USDT",
    "open_interest": 880267.87,
    "volume_24h": 894970.9470231544
  },
  {
    "symbol": "HAEDAL_USDT",
    "open_interest": 876524.9,
    "volume_24h": 1782921.0383025957
  },
  {
    "symbol": "SKYAI_USDT",
    "open_interest": 876403.66,
    "volume_24h": 427837.53362879413
  },
  {
    "symbol": "BANANAS31_USDT",
    "open_interest": 856748.01,
    "volume_24h": 28495969.705262963
  },
  {
    "symbol": "C_USDT",
    "open_interest": 856236.17,
    "volume_24h": 31540976.376988195
  },
  {
    "symbol": "PYTH_USDT",
    "open_interest": 849064.51,
    "volume_24h": 431205.2332215139
  },
  {
    "symbol": "GORK_USDT",
    "open_interest": 846409.48,
    "volume_24h": 410106.1749932907
  },
  {
    "symbol": "AIXBT_USDT",
    "open_interest": 841071.05,
    "volume_24h": 7024361.626352598
  },
  {
    "symbol": "FTT_USDT",
    "open_interest": 839694.06,
    "volume_24h": 235382.59500064448
  },
  {
    "symbol": "IO_USDT",
    "open_interest": 839507.84,
    "volume_24h": 3117405.959550522
  },
  {
    "symbol": "ZRO_USDT",
    "open_interest": 829048.75,
    "volume_24h": 145844.26533852864
  },
  {
    "symbol": "ZRC_USDT",
    "open_interest": 826278.87,
    "volume_24h": 13760438.005832292
  },
  {
    "symbol": "RAY_USDT",
    "open_interest": 824062.17,
    "volume_24h": 931632.0790931183
  },
  {
    "symbol": "HSK_USDT",
    "open_interest": 818753.82,
    "volume_24h": 178595.38848580504
  },
  {
    "symbol": "NEIROCTO_USDT",
    "open_interest": 813318.3,
    "volume_24h": 1730130.7763915572
  },
  {
    "symbol": "EPIC_USDT",
    "open_interest": 811738.38,
    "volume_24h": 3019805.8518135278
  },
  {
    "symbol": "ARKM_USDT",
    "open_interest": 784629.61,
    "volume_24h": 2816536.1295633935
  },
  {
    "symbol": "W_USDT",
    "open_interest": 760098.29,
    "volume_24h": 3082843.1166551244
  },
  {
    "symbol": "AXS_USDT",
    "open_interest": 759093.43,
    "volume_24h": 274166.04770888883
  },
  {
    "symbol": "INIT_USDT",
    "open_interest": 737967.05,
    "volume_24h": 3478281.4206516384
  },
  {
    "symbol": "NXPC_USDT",
    "open_interest": 692680.0,
    "volume_24h": 1795134.4765304646
  },
  {
    "symbol": "AERO_USDT",
    "open_interest": 690796.25,
    "volume_24h": 2287684.0304299057
  },
  {
    "symbol": "MANA_USDT",
    "open_interest": 682939.56,
    "volume_24h": 299220.34199711215
  },
  {
    "symbol": "THETA_USDT",
    "open_interest": 674537.27,
    "volume_24h": 2960050.166553849
  },
  {
    "symbol": "PEAQ_USDT",
    "open_interest": 670818.4,
    "volume_24h": 1339338.9001053355
  },
  {
    "symbol": "YGG_USDT",
    "open_interest": 658358.75,
    "volume_24h": 340549.20570194995
  },
  {
    "symbol": "CHZ_USDT",
    "open_interest": 657555.57,
    "volume_24h": 370797.62827368325
  },
  {
    "symbol": "DEGEN_USDT",
    "open_interest": 654912.61,
    "volume_24h": 400938.6474508176
  },
  {
    "symbol": "USELESS_USDT",
    "open_interest": 650514.03,
    "volume_24h": 3866083.2604635316
  },
  {
    "symbol": "HIPPO_USDT",
    "open_interest": 643168.9,
    "volume_24h": 1143176.8568586304
  },
  {
    "symbol": "XAI_USDT",
    "open_interest": 637001.68,
    "volume_24h": 2993052.555701804
  },
  {
    "symbol": "RVN_USDT",
    "open_interest": 632640.06,
    "volume_24h": 59846.65200176674
  },
  {
    "symbol": "IMX_USDT",
    "open_interest": 627394.35,
    "volume_24h": 1682108.2540624442
  },
  {
    "symbol": "GRIFFAIN_USDT",
    "open_interest": 625805.35,
    "volume_24h": 1685184.2628594472
  },
  {
    "symbol": "NIL_USDT",
    "open_interest": 623784.36,
    "volume_24h": 2191910.458125271
  },
  {
    "symbol": "GRT_USDT",
    "open_interest": 623362.83,
    "volume_24h": 4198571.42218088
  },
  {
    "symbol": "MOG_USDT",
    "open_interest": 618232.53,
    "volume_24h": 578219.3066945975
  },
  {
    "symbol": "BMT_USDT",
    "open_interest": 603261.46,
    "volume_24h": 1142736.66354411
  },
  {
    "symbol": "AVAAI_USDT",
    "open_interest": 601240.91,
    "volume_24h": 1424299.185436002
  },
  {
    "symbol": "KSM_USDT",
    "open_interest": 593952.89,
    "volume_24h": 1496180.5541238056
  },
  {
    "symbol": "HFT_USDT",
    "open_interest": 591959.19,
    "volume_24h": 2509861.7658902723
  },
  {
    "symbol": "ESPORTS_USDT",
    "open_interest": 590076.75,
    "volume_24h": 81462017.71940213
  },
  {
    "symbol": "VRA_USDT",
    "open_interest": 586113.68,
    "volume_24h": 770508.8883991766
  },
  {
    "symbol": "CHILLGUY_USDT",
    "open_interest": 581851.88,
    "volume_24h": 1255343.2946008993
  },
  {
    "symbol": "CAT_USDT",
    "open_interest": 573806.17,
    "volume_24h": 2330468.49125163
  },
  {
    "symbol": "RED_USDT",
    "open_interest": 573743.27,
    "volume_24h": 3234263.1927995672
  },
  {
    "symbol": "SNX_USDT",
    "open_interest": 571356.72,
    "volume_24h": 1821292.2817928393
  },
  {
    "symbol": "BLUR_USDT",
    "open_interest": 568322.61,
    "volume_24h": 2168586.4557320736
  },
  {
    "symbol": "ASP_USDT",
    "open_interest": 565843.27,
    "volume_24h": 3885330.3548229528
  },
  {
    "symbol": "JASMY_USDT",
    "open_interest": 563680.65,
    "volume_24h": 2573243.274336162
  },
  {
    "symbol": "FLOCK_USDT",
    "open_interest": 561132.58,
    "volume_24h": 734020.60851007
  },
  {
    "symbol": "MEMEFI_USDT",
    "open_interest": 555177.3,
    "volume_24h": 392763.88704395556
  },
  {
    "symbol": "ZKJ_USDT",
    "open_interest": 551811.83,
    "volume_24h": 122044.7808479626
  },
  {
    "symbol": "JELLYJELLY_USDT",
    "open_interest": 541218.55,
    "volume_24h": 967353.9992015058
  },
  {
    "symbol": "USTC_USDT",
    "open_interest": 536001.87,
    "volume_24h": 3281568.8624902274
  },
  {
    "symbol": "DEEP_USDT",
    "open_interest": 534986.48,
    "volume_24h": 3236421.3440025123
  },
  {
    "symbol": "NOT_USDT",
    "open_interest": 533387.7,
    "volume_24h": 704684.1842636559
  },
  {
    "symbol": "ARC_USDT",
    "open_interest": 533039.81,
    "volume_24h": 1425198.1500563314
  },
  {
    "symbol": "HOME_USDT",
    "open_interest": 532898.21,
    "volume_24h": 1975688.343501876
  },
  {
    "symbol": "PLUME_USDT",
    "open_interest": 532352.28,
    "volume_24h": 3105413.6604870968
  },
  {
    "symbol": "SUPER_USDT",
    "open_interest": 531891.29,
    "volume_24h": 18271010.91301447
  },
  {
    "symbol": "ICNT_USDT",
    "open_interest": 530087.57,
    "volume_24h": 4269219.22807894
  },
  {
    "symbol": "COW_USDT",
    "open_interest": 528791.9,
    "volume_24h": 1645274.5240441768
  },
  {
    "symbol": "SONIC_USDT",
    "open_interest": 528427.23,
    "volume_24h": 75196.80788947012
  },
  {
    "symbol": "DOLO_USDT",
    "open_interest": 527600.1,
    "volume_24h": 909044.4417589642
  },
  {
    "symbol": "NEO_USDT",
    "open_interest": 527342.98,
    "volume_24h": 1147234.0863174745
  },
  {
    "symbol": "IOTA_USDT",
    "open_interest": 516136.99,
    "volume_24h": 134665.35560714305
  },
  {
    "symbol": "HUMA_USDT",
    "open_interest": 512942.03,
    "volume_24h": 2180802.4052008744
  },
  {
    "symbol": "BABY_USDT",
    "open_interest": 512834.86,
    "volume_24h": 2161438.183332962
  },
  {
    "symbol": "SUNDOG_USDT",
    "open_interest": 512651.4,
    "volume_24h": 1562369.7805469136
  },
  {
    "symbol": "UXLINK_USDT",
    "open_interest": 508501.38,
    "volume_24h": 602967.152181534
  },
  {
    "symbol": "ASR_USDT",
    "open_interest": 504557.12,
    "volume_24h": 3367115.761455371
  },
  {
    "symbol": "ALPACA_USDT",
    "open_interest": 502428.27,
    "volume_24h": 938854.8465097988
  },
  {
    "symbol": "VANRY_USDT",
    "open_interest": 501086.94,
    "volume_24h": 1270764.872603731
  },
  {
    "symbol": "TA_USDT",
    "open_interest": 497578.68,
    "volume_24h": 2958642.2269229004
  },
  {
    "symbol": "RARE_USDT",
    "open_interest": 496642.54,
    "volume_24h": 6990548.722074165
  },
  {
    "symbol": "AERGO_USDT",
    "open_interest": 490934.4,
    "volume_24h": 904099.0429205133
  },
  {
    "symbol": "RSR_USDT",
    "open_interest": 490533.79,
    "volume_24h": 1435261.5706944622
  },
  {
    "symbol": "MBABYDOGE_USDT",
    "open_interest": 485567.28,
    "volume_24h": 250849.75951531142
  },
  {
    "symbol": "CETUS_USDT",
    "open_interest": 483805.32,
    "volume_24h": 2483896.8813427864
  },
  {
    "symbol": "CORE_USDT",
    "open_interest": 481374.7,
    "volume_24h": 1126663.8669626089
  },
  {
    "symbol": "QUBIC_USDT",
    "open_interest": 477695.44,
    "volume_24h": 348901.54576919676
  },
  {
    "symbol": "XDC_USDT",
    "open_interest": 475659.56,
    "volume_24h": 264375.7936005639
  },
  {
    "symbol": "AGT_USDT",
    "open_interest": 470670.4,
    "volume_24h": 1437234.230961815
  },
  {
    "symbol": "FHE_USDT",
    "open_interest": 468850.08,
    "volume_24h": 2518414.761829187
  },
  {
    "symbol": "VIC_USDT",
    "open_interest": 468810.43,
    "volume_24h": 16969726.82194032
  },
  {
    "symbol": "VVV_USDT",
    "open_interest": 466001.92,
    "volume_24h": 901671.4721973542
  },
  {
    "symbol": "RHEA_USDT",
    "open_interest": 459781.65,
    "volume_24h": 49068437.41961836
  },
  {
    "symbol": "EGLD_USDT",
    "open_interest": 453327.78,
    "volume_24h": 124174.23915857355
  },
  {
    "symbol": "OBOL_USDT",
    "open_interest": 449693.44,
    "volume_24h": 1051655.0956933796
  },
  {
    "symbol": "DOGS_USDT",
    "open_interest": 449213.33,
    "volume_24h": 2936300.8684603856
  },
  {
    "symbol": "BIGTIME_USDT",
    "open_interest": 447751.75,
    "volume_24h": 1956338.2623439885
  },
  {
    "symbol": "LA_USDT",
    "open_interest": 447419.92,
    "volume_24h": 1261348.8917308147
  },
  {
    "symbol": "LAYER_USDT",
    "open_interest": 446483.79,
    "volume_24h": 256608.6746725185
  },
  {
    "symbol": "CKB_USDT",
    "open_interest": 438042.72,
    "volume_24h": 8824382.905733364
  },
  {
    "symbol": "VELO_USDT",
    "open_interest": 436630.51,
    "volume_24h": 1594955.6453605655
  },
  {
    "symbol": "VET_USDT",
    "open_interest": 431693.6,
    "volume_24h": 257093.2060595106
  },
  {
    "symbol": "XCN_USDT",
    "open_interest": 423257.16,
    "volume_24h": 1435882.8140307923
  },
  {
    "symbol": "KAVA_USDT",
    "open_interest": 421704.46,
    "volume_24h": 1134106.9747856383
  },
  {
    "symbol": "KNC_USDT",
    "open_interest": 419746.09,
    "volume_24h": 11244971.991539802
  },
  {
    "symbol": "WAL_USDT",
    "open_interest": 418344.05,
    "volume_24h": 264909.07880020275
  },
  {
    "symbol": "TOSHI_USDT",
    "open_interest": 418149.23,
    "volume_24h": 724712.7895223756
  },
  {
    "symbol": "ZRX_USDT",
    "open_interest": 417978.51,
    "volume_24h": 190319.3754317138
  },
  {
    "symbol": "ELX_USDT",
    "open_interest": 416248.62,
    "volume_24h": 2361988.827887653
  },
  {
    "symbol": "FWOG_USDT",
    "open_interest": 412268.53,
    "volume_24h": 755293.9324562217
  },
  {
    "symbol": "1INCH_USDT",
    "open_interest": 410008.21,
    "volume_24h": 466929.78817747947
  },
  {
    "symbol": "TOKEN_USDT",
    "open_interest": 407944.98,
    "volume_24h": 436614.4085103268
  },
  {
    "symbol": "MERL_USDT",
    "open_interest": 406057.3,
    "volume_24h": 1475637.9432550978
  },
  {
    "symbol": "ACH_USDT",
    "open_interest": 402795.74,
    "volume_24h": 167463.82203637593
  },
  {
    "symbol": "PLAY_USDT",
    "open_interest": 402719.9,
    "volume_24h": 2956910.040412346
  },
  {
    "symbol": "MYRO_USDT",
    "open_interest": 398781.5,
    "volume_24h": 1430732.0871544431
  },
  {
    "symbol": "MEME_USDT",
    "open_interest": 398291.16,
    "volume_24h": 1026626.2738021181
  },
  {
    "symbol": "NERO_USDT",
    "open_interest": 392432.96,
    "volume_24h": 3007775.104191657
  },
  {
    "symbol": "ANIME_USDT",
    "open_interest": 389562.01,
    "volume_24h": 2702719.592728522
  },
  {
    "symbol": "VANA_USDT",
    "open_interest": 389262.36,
    "volume_24h": 984779.0015456085
  },
  {
    "symbol": "TANSSI_USDT",
    "open_interest": 384246.54,
    "volume_24h": 1483192.7150627663
  },
  {
    "symbol": "DBR_USDT",
    "open_interest": 384245.86,
    "volume_24h": 862159.4800440418
  },
  {
    "symbol": "GMT_USDT",
    "open_interest": 379369.84,
    "volume_24h": 143456.73861858877
  },
  {
    "symbol": "MANTA_USDT",
    "open_interest": 379156.8,
    "volume_24h": 1087334.6210342892
  },
  {
    "symbol": "RFC_USDT",
    "open_interest": 375594.95,
    "volume_24h": 393419.6094787455
  },
  {
    "symbol": "DMC_USDT",
    "open_interest": 374951.72,
    "volume_24h": 1061392.225964928
  },
  {
    "symbol": "EPT_USDT",
    "open_interest": 374150.38,
    "volume_24h": 122957.20349725534
  },
  {
    "symbol": "MAJOR_USDT",
    "open_interest": 373071.06,
    "volume_24h": 980185.8833239926
  },
  {
    "symbol": "XCH_USDT",
    "open_interest": 372365.91,
    "volume_24h": 409289.890284434
  },
  {
    "symbol": "FRAG_USDT",
    "open_interest": 370078.41,
    "volume_24h": 2423104.928976348
  },
  {
    "symbol": "ES_USDT",
    "open_interest": 369274.4,
    "volume_24h": 774772.0101833261
  },
  {
    "symbol": "SOLV_USDT",
    "open_interest": 368604.52,
    "volume_24h": 1811010.9318695383
  },
  {
    "symbol": "MINA_USDT",
    "open_interest": 368165.59,
    "volume_24h": 90990.4246571555
  },
  {
    "symbol": "LUNC_USDT",
    "open_interest": 365338.15,
    "volume_24h": 209243.94751085347
  },
  {
    "symbol": "SIGN_USDT",
    "open_interest": 365327.31,
    "volume_24h": 573306.7256096414
  },
  {
    "symbol": "DRIFT_USDT",
    "open_interest": 364465.44,
    "volume_24h": 2438021.793091522
  },
  {
    "symbol": "LISTA_USDT",
    "open_interest": 361194.53,
    "volume_24h": 2051280.825605196
  },
  {
    "symbol": "AIN_USDT",
    "open_interest": 359536.83,
    "volume_24h": 1320865.0235684714
  },
  {
    "symbol": "WOO_USDT",
    "open_interest": 358752.42,
    "volume_24h": 2155317.519921722
  },
  {
    "symbol": "VELVET_USDT",
    "open_interest": 355480.0,
    "volume_24h": 913055.8322407509
  },
  {
    "symbol": "GMX_USDT",
    "open_interest": 355372.2,
    "volume_24h": 1828483.3955539374
  },
  {
    "symbol": "CRCLX_USDT",
    "open_interest": 350674.45,
    "volume_24h": 1555389.929909301
  },
  {
    "symbol": "MORPHO_USDT",
    "open_interest": 350259.66,
    "volume_24h": 1587554.2408972562
  },
  {
    "symbol": "THE_USDT",
    "open_interest": 349475.84,
    "volume_24h": 3015310.5019262
  },
  {
    "symbol": "UMA_USDT",
    "open_interest": 348789.86,
    "volume_24h": 683453.125656083
  },
  {
    "symbol": "SNT_USDT",
    "open_interest": 347196.47,
    "volume_24h": 1417557.3257824944
  },
  {
    "symbol": "BR_USDT",
    "open_interest": 344597.29,
    "volume_24h": 801968.4455973962
  },
  {
    "symbol": "C98_USDT",
    "open_interest": 340799.07,
    "volume_24h": 3316233.980043263
  },
  {
    "symbol": "ZEUS_USDT",
    "open_interest": 335022.67,
    "volume_24h": 442602.56487859454
  },
  {
    "symbol": "DOOD_USDT",
    "open_interest": 333891.33,
    "volume_24h": 302829.61696722615
  },
  {
    "symbol": "GUN_USDT",
    "open_interest": 333858.17,
    "volume_24h": 2148036.628850186
  },
  {
    "symbol": "BLAST_USDT",
    "open_interest": 332570.26,
    "volume_24h": 3380907.7820423227
  },
  {
    "symbol": "B3_USDT",
    "open_interest": 332090.25,
    "volume_24h": 3199146.9295676304
  },
  {
    "symbol": "X_USDT",
    "open_interest": 330267.48,
    "volume_24h": 159328.40882630434
  },
  {
    "symbol": "DUCK_USDT",
    "open_interest": 327713.17,
    "volume_24h": 4295882.885052616
  },
  {
    "symbol": "VOXEL_USDT",
    "open_interest": 327363.25,
    "volume_24h": 1193211.600283006
  },
  {
    "symbol": "HNT_USDT",
    "open_interest": 324733.62,
    "volume_24h": 1003298.4703855145
  },
  {
    "symbol": "CYBER_USDT",
    "open_interest": 324562.46,
    "volume_24h": 184229.4179352406
  },
  {
    "symbol": "BDXN_USDT",
    "open_interest": 322802.78,
    "volume_24h": 1269472.9692578493
  },
  {
    "symbol": "SAGA_USDT",
    "open_interest": 321732.27,
    "volume_24h": 1551390.9561504226
  },
  {
    "symbol": "NAORIS_USDT",
    "open_interest": 319772.7,
    "volume_24h": 70750348.1091957
  },
  {
    "symbol": "CVX_USDT",
    "open_interest": 318267.66,
    "volume_24h": 3561850.791717069
  },
  {
    "symbol": "HMSTR_USDT",
    "open_interest": 312318.88,
    "volume_24h": 756058.1975608772
  },
  {
    "symbol": "MOCA_USDT",
    "open_interest": 306318.17,
    "volume_24h": 1245386.9089777928
  },
  {
    "symbol": "ENJ_USDT",
    "open_interest": 306271.72,
    "volume_24h": 937681.6937898817
  },
  {
    "symbol": "BB_USDT",
    "open_interest": 305347.03,
    "volume_24h": 2414538.3667478003
  },
  {
    "symbol": "SSV_USDT",
    "open_interest": 304928.95,
    "volume_24h": 4544005.939937084
  },
  {
    "symbol": "AUCTION_USDT",
    "open_interest": 304838.77,
    "volume_24h": 1065340.36385826
  },
  {
    "symbol": "FIDA_USDT",
    "open_interest": 303630.45,
    "volume_24h": 3166891.534750139
  },
  {
    "symbol": "SXT_USDT",
    "open_interest": 302672.44,
    "volume_24h": 549427.1791315881
  },
  {
    "symbol": "TAIKO_USDT",
    "open_interest": 301631.5,
    "volume_24h": 2922108.3050141134
  },
  {
    "symbol": "IOTX_USDT",
    "open_interest": 298880.95,
    "volume_24h": 3137547.8214646145
  },
  {
    "symbol": "PORT3_USDT",
    "open_interest": 297887.87,
    "volume_24h": 398556.1390232017
  },
  {
    "symbol": "AKT_USDT",
    "open_interest": 297006.6,
    "volume_24h": 1374692.6437509872
  },
  {
    "symbol": "DFDVX_USDT",
    "open_interest": 296068.98,
    "volume_24h": 1333869.23336645
  },
  {
    "symbol": "CTK_USDT",
    "open_interest": 294796.8,
    "volume_24h": 1121950.5073459693
  },
  {
    "symbol": "DYM_USDT",
    "open_interest": 293048.06,
    "volume_24h": 527238.0543525205
  },
  {
    "symbol": "PORTAL_USDT",
    "open_interest": 292081.95,
    "volume_24h": 929556.9184024164
  },
  {
    "symbol": "PUFFER_USDT",
    "open_interest": 291443.96,
    "volume_24h": 1571059.490227302
  },
  {
    "symbol": "PROMPT_USDT",
    "open_interest": 290204.32,
    "volume_24h": 601391.394989435
  },
  {
    "symbol": "BROCCOLI_USDT",
    "open_interest": 288708.12,
    "volume_24h": 1448611.6092127617
  },
  {
    "symbol": "METIS_USDT",
    "open_interest": 286041.76,
    "volume_24h": 742593.4282807466
  },
  {
    "symbol": "RWA_USDT",
    "open_interest": 286014.24,
    "volume_24h": 1215092.3414730618
  },
  {
    "symbol": "POKT_USDT",
    "open_interest": 283021.23,
    "volume_24h": 48523.659016454076
  },
  {
    "symbol": "DIA_USDT",
    "open_interest": 281754.09,
    "volume_24h": 1386730.4061162125
  },
  {
    "symbol": "CSPR_USDT",
    "open_interest": 280607.15,
    "volume_24h": 54248.79078367016
  },
  {
    "symbol": "SLERF_USDT",
    "open_interest": 280601.89,
    "volume_24h": 799421.570103604
  },
  {
    "symbol": "BAT_USDT",
    "open_interest": 279540.4,
    "volume_24h": 2304496.3555582548
  },
  {
    "symbol": "CELO_USDT",
    "open_interest": 278467.84,
    "volume_24h": 1454055.0432992184
  },
  {
    "symbol": "SUPRA_USDT",
    "open_interest": 278278.43,
    "volume_24h": 1035729.3003743015
  },
  {
    "symbol": "PAAL_USDT",
    "open_interest": 277745.58,
    "volume_24h": 112170.9275929291
  },
  {
    "symbol": "SUN_USDT",
    "open_interest": 276614.23,
    "volume_24h": 598066.7416386415
  },
  {
    "symbol": "CARV_USDT",
    "open_interest": 272927.17,
    "volume_24h": 143900.77670943216
  },
  {
    "symbol": "NVDAX_USDT",
    "open_interest": 271183.64,
    "volume_24h": 559918.0648652163
  },
  {
    "symbol": "MDT_USDT",
    "open_interest": 268561.09,
    "volume_24h": 583330.7783869655
  },
  {
    "symbol": "FLOW_USDT",
    "open_interest": 265877.22,
    "volume_24h": 2084352.118012817
  },
  {
    "symbol": "LUMIA_USDT",
    "open_interest": 263624.9,
    "volume_24h": 867562.4576711617
  },
  {
    "symbol": "A2Z_USDT",
    "open_interest": 262757.61,
    "volume_24h": 4095305.295960672
  },
  {
    "symbol": "QNT_USDT",
    "open_interest": 262010.77,
    "volume_24h": 1130153.899479023
  },
  {
    "symbol": "RPL_USDT",
    "open_interest": 261382.99,
    "volume_24h": 3007838.723053607
  },
  {
    "symbol": "SKATE_USDT",
    "open_interest": 261304.27,
    "volume_24h": 1187416.895517022
  },
  {
    "symbol": "B2_USDT",
    "open_interest": 260240.05,
    "volume_24h": 450643.54296605446
  },
  {
    "symbol": "LQTY_USDT",
    "open_interest": 259648.64,
    "volume_24h": 3239615.1911286013
  },
  {
    "symbol": "MEW_USDT",
    "open_interest": 259110.43,
    "volume_24h": 317599.88843904715
  },
  {
    "symbol": "OG_USDT",
    "open_interest": 255028.31,
    "volume_24h": 1761358.3735163186
  },
  {
    "symbol": "NC_USDT",
    "open_interest": 250515.08,
    "volume_24h": 6090382.7026615245
  },
  {
    "symbol": "JST_USDT",
    "open_interest": 250374.48,
    "volume_24h": 1117124.4588628097
  },
  {
    "symbol": "SLP_USDT",
    "open_interest": 248331.52,
    "volume_24h": 344681.37881635077
  },
  {
    "symbol": "TAKER_USDT",
    "open_interest": 245449.31,
    "volume_24h": 632880.2156414363
  },
  {
    "symbol": "TSLAX_USDT",
    "open_interest": 241928.38,
    "volume_24h": 443354.26610362565
  },
  {
    "symbol": "XEM_USDT",
    "open_interest": 240904.99,
    "volume_24h": 539918.461679077
  },
  {
    "symbol": "ROSE_USDT",
    "open_interest": 237929.8,
    "volume_24h": 1416506.364915664
  },
  {
    "symbol": "BANK_USDT",
    "open_interest": 236780.74,
    "volume_24h": 417981.7444278182
  },
  {
    "symbol": "SHELL_USDT",
    "open_interest": 232586.86,
    "volume_24h": 1072151.5318369218
  },
  {
    "symbol": "KMNO_USDT",
    "open_interest": 232272.33,
    "volume_24h": 1382793.0063832477
  },
  {
    "symbol": "CVC_USDT",
    "open_interest": 232070.98,
    "volume_24h": 990691.5268472468
  },
  {
    "symbol": "CATI_USDT",
    "open_interest": 229433.79,
    "volume_24h": 1161079.4775836426
  },
  {
    "symbol": "ONE_USDT",
    "open_interest": 227594.28,
    "volume_24h": 1537079.987014093
  },
  {
    "symbol": "YFI_USDT",
    "open_interest": 226998.77,
    "volume_24h": 117856.15927998371
  },
  {
    "symbol": "PRCL_USDT",
    "open_interest": 222820.84,
    "volume_24h": 937807.9006734481
  },
  {
    "symbol": "BAN_USDT",
    "open_interest": 220909.39,
    "volume_24h": 1287982.5923729967
  },
  {
    "symbol": "SD_USDT",
    "open_interest": 220624.25,
    "volume_24h": 1189330.0845029347
  },
  {
    "symbol": "AEVO_USDT",
    "open_interest": 220604.79,
    "volume_24h": 354935.37902002275
  },
  {
    "symbol": "MAT_USDT",
    "open_interest": 219569.99,
    "volume_24h": 8812663.624547431
  },
  {
    "symbol": "WAVES_USDT",
    "open_interest": 218469.41,
    "volume_24h": 1257041.2145194882
  },
  {
    "symbol": "FIO_USDT",
    "open_interest": 218420.29,
    "volume_24h": 154037.28890296724
  },
  {
    "symbol": "AIOT_USDT",
    "open_interest": 217315.01,
    "volume_24h": 228514.16088593184
  },
  {
    "symbol": "FLR_USDT",
    "open_interest": 216722.81,
    "volume_24h": 1314004.6422647804
  },
  {
    "symbol": "ACT_USDT",
    "open_interest": 214625.41,
    "volume_24h": 1183150.631803637
  },
  {
    "symbol": "SYN_USDT",
    "open_interest": 214168.77,
    "volume_24h": 1927997.606394231
  },
  {
    "symbol": "PONKE_USDT",
    "open_interest": 213888.04,
    "volume_24h": 2077417.3099432597
  },
  {
    "symbol": "XION_USDT",
    "open_interest": 212819.89,
    "volume_24h": 1655977.929905651
  },
  {
    "symbol": "PHA_USDT",
    "open_interest": 212620.3,
    "volume_24h": 890233.0607938509
  },
  {
    "symbol": "TAI_USDT",
    "open_interest": 211376.82,
    "volume_24h": 2873993.1319525945
  },
  {
    "symbol": "STO_USDT",
    "open_interest": 207388.25,
    "volume_24h": 1137886.8071974723
  },
  {
    "symbol": "KDA_USDT",
    "open_interest": 206777.52,
    "volume_24h": 1319322.4331929272
  },
  {
    "symbol": "LUNA_USDT",
    "open_interest": 206011.43,
    "volume_24h": 138767.1467134213
  },
  {
    "symbol": "GIGA_USDT",
    "open_interest": 205300.5,
    "volume_24h": 1167221.695597688
  },
  {
    "symbol": "KOMA_USDT",
    "open_interest": 205191.25,
    "volume_24h": 77570.37152734495
  },
  {
    "symbol": "FUEL_USDT",
    "open_interest": 205065.1,
    "volume_24h": 205938.26990746442
  },
  {
    "symbol": "SCRT_USDT",
    "open_interest": 204867.24,
    "volume_24h": 762512.4761671583
  },
  {
    "symbol": "PRIME_USDT",
    "open_interest": 204156.02,
    "volume_24h": 483792.93967395165
  },
  {
    "symbol": "MGO_USDT",
    "open_interest": 204147.01,
    "volume_24h": 18793.934594446564
  },
  {
    "symbol": "PROM_USDT",
    "open_interest": 203035.86,
    "volume_24h": 2522659.3943183217
  },
  {
    "symbol": "AGLD_USDT",
    "open_interest": 199738.24,
    "volume_24h": 863539.5296468468
  },
  {
    "symbol": "OL_USDT",
    "open_interest": 199488.11,
    "volume_24h": 618917.9989276882
  },
  {
    "symbol": "GNO_USDT",
    "open_interest": 198953.56,
    "volume_24h": 52951.836539353426
  },
  {
    "symbol": "ZIL_USDT",
    "open_interest": 198914.83,
    "volume_24h": 2233042.606900397
  },
  {
    "symbol": "SAFE_USDT",
    "open_interest": 197359.11,
    "volume_24h": 146308.11738720362
  },
  {
    "symbol": "SCR_USDT",
    "open_interest": 194457.19,
    "volume_24h": 61408.71240281777
  },
  {
    "symbol": "MILK_USDT",
    "open_interest": 190939.06,
    "volume_24h": 30091.08876432092
  },
  {
    "symbol": "CGPT_USDT",
    "open_interest": 190522.43,
    "volume_24h": 1821697.38646017
  },
  {
    "symbol": "IDOL_USDT",
    "open_interest": 189038.04,
    "volume_24h": 364023.82444222196
  },
  {
    "symbol": "SQD_USDT",
    "open_interest": 186067.38,
    "volume_24h": 291024.8014888417
  },
  {
    "symbol": "UNITE_USDT",
    "open_interest": 184729.72,
    "volume_24h": 978135.6177643149
  },
  {
    "symbol": "BANANA_USDT",
    "open_interest": 184690.86,
    "volume_24h": 518433.9106258429
  },
  {
    "symbol": "LRC_USDT",
    "open_interest": 184482.44,
    "volume_24h": 2317498.494957309
  },
  {
    "symbol": "RSS3_USDT",
    "open_interest": 181400.63,
    "volume_24h": 802661.6357982791
  },
  {
    "symbol": "RON_USDT",
    "open_interest": 181279.3,
    "volume_24h": 56628.89446926251
  },
  {
    "symbol": "ZKWASM_USDT",
    "open_interest": 181254.32,
    "volume_24h": 171850.57258162534
  },
  {
    "symbol": "BNT_USDT",
    "open_interest": 180833.87,
    "volume_24h": 3763087.0105535714
  },
  {
    "symbol": "REX_USDT",
    "open_interest": 180321.77,
    "volume_24h": 806746.0930942064
  },
  {
    "symbol": "MBOX_USDT",
    "open_interest": 176987.27,
    "volume_24h": 467139.5194117748
  },
  {
    "symbol": "BAKE_USDT",
    "open_interest": 175636.08,
    "volume_24h": 77242.15626359273
  },
  {
    "symbol": "CPOOL_USDT",
    "open_interest": 172869.91,
    "volume_24h": 697981.3193498678
  },
  {
    "symbol": "CTSI_USDT",
    "open_interest": 171945.35,
    "volume_24h": 2384217.60704605
  },
  {
    "symbol": "DEXE_USDT",
    "open_interest": 171277.58,
    "volume_24h": 1551963.9509309253
  },
  {
    "symbol": "TAG_USDT",
    "open_interest": 171032.27,
    "volume_24h": 318965.39972503943
  },
  {
    "symbol": "PIXEL_USDT",
    "open_interest": 170231.77,
    "volume_24h": 1038987.5606875683
  },
  {
    "symbol": "ALPHA_USDT",
    "open_interest": 170069.11,
    "volume_24h": 935074.2839805386
  },
  {
    "symbol": "FB_USDT",
    "open_interest": 168768.98,
    "volume_24h": 61182.42985254048
  },
  {
    "symbol": "REZ_USDT",
    "open_interest": 166048.65,
    "volume_24h": 479422.25821010454
  },
  {
    "symbol": "FLUX_USDT",
    "open_interest": 165496.61,
    "volume_24h": 514118.9229191336
  },
  {
    "symbol": "GAS_USDT",
    "open_interest": 163608.9,
    "volume_24h": 1357456.019003605
  },
  {
    "symbol": "CTC_USDT",
    "open_interest": 162917.94,
    "volume_24h": 2400718.0255626147
  },
  {
    "symbol": "PFVS_USDT",
    "open_interest": 162561.32,
    "volume_24h": 44958.503023562895
  },
  {
    "symbol": "ACE_USDT",
    "open_interest": 162189.98,
    "volume_24h": 502813.35761419457
  },
  {
    "symbol": "ICX_USDT",
    "open_interest": 160936.81,
    "volume_24h": 2491322.063642375
  },
  {
    "symbol": "GPS_USDT",
    "open_interest": 160389.8,
    "volume_24h": 572027.0187265812
  },
  {
    "symbol": "GLM_USDT",
    "open_interest": 158761.16,
    "volume_24h": 242711.87964028592
  },
  {
    "symbol": "QTUM_USDT",
    "open_interest": 158715.87,
    "volume_24h": 41384.5571832039
  },
  {
    "symbol": "ROAM_USDT",
    "open_interest": 158651.93,
    "volume_24h": 496851.6538519078
  },
  {
    "symbol": "COTI_USDT",
    "open_interest": 158540.0,
    "volume_24h": 1281254.7394518016
  },
  {
    "symbol": "ILV_USDT",
    "open_interest": 158482.7,
    "volume_24h": 1705919.450691642
  },
  {
    "symbol": "HEI_USDT",
    "open_interest": 158208.58,
    "volume_24h": 4782649.78426194
  },
  {
    "symbol": "LOOKS_USDT",
    "open_interest": 158028.9,
    "volume_24h": 712420.6635843385
  },
  {
    "symbol": "API3_USDT",
    "open_interest": 155916.32,
    "volume_24h": 941958.975238044
  },
  {
    "symbol": "BROCCOLIF3B_USDT",
    "open_interest": 154990.91,
    "volume_24h": 53198.43870952097
  },
  {
    "symbol": "CHR_USDT",
    "open_interest": 154651.43,
    "volume_24h": 2019972.1684255677
  },
  {
    "symbol": "AVAIL_USDT",
    "open_interest": 153957.1,
    "volume_24h": 241088.4134695664
  },
  {
    "symbol": "MTL_USDT",
    "open_interest": 153772.12,
    "volume_24h": 972127.1655989813
  },
  {
    "symbol": "TWT_USDT",
    "open_interest": 152936.74,
    "volume_24h": 926608.5121990663
  },
  {
    "symbol": "BAL_USDT",
    "open_interest": 151624.08,
    "volume_24h": 66524.59023685835
  },
  {
    "symbol": "CHESS_USDT",
    "open_interest": 149950.42,
    "volume_24h": 973102.5795371899
  },
  {
    "symbol": "XNY_USDT",
    "open_interest": 148812.31,
    "volume_24h": 683498.7016981521
  },
  {
    "symbol": "COINX_USDT",
    "open_interest": 148704.26,
    "volume_24h": 271019.39192967745
  },
  {
    "symbol": "MAVIA_USDT",
    "open_interest": 148703.82,
    "volume_24h": 615252.105830437
  },
  {
    "symbol": "SIREN_USDT",
    "open_interest": 147401.15,
    "volume_24h": 1009641.8167021653
  },
  {
    "symbol": "ATA_USDT",
    "open_interest": 146013.06,
    "volume_24h": 1799664.7594565812
  },
  {
    "symbol": "BAND_USDT",
    "open_interest": 145556.43,
    "volume_24h": 1979965.2602500482
  },
  {
    "symbol": "RCADE_USDT",
    "open_interest": 145301.02,
    "volume_24h": 210923.67702599987
  },
  {
    "symbol": "AIOZ_USDT",
    "open_interest": 145176.48,
    "volume_24h": 738913.1984087777
  },
  {
    "symbol": "IDEX_USDT",
    "open_interest": 143879.01,
    "volume_24h": 865650.0165492089
  },
  {
    "symbol": "HOUSE_USDT",
    "open_interest": 141876.52,
    "volume_24h": 522618.1336320373
  },
  {
    "symbol": "ACX_USDT",
    "open_interest": 141041.97,
    "volume_24h": 759429.5132434553
  },
  {
    "symbol": "BSW_USDT",
    "open_interest": 140443.77,
    "volume_24h": 1695777.7166346381
  },
  {
    "symbol": "EDU_USDT",
    "open_interest": 139115.34,
    "volume_24h": 1244103.3387426753
  },
  {
    "symbol": "ALICE_USDT",
    "open_interest": 138807.49,
    "volume_24h": 583029.9139010591
  },
  {
    "symbol": "TRU_USDT",
    "open_interest": 138104.87,
    "volume_24h": 2124829.8780363463
  },
  {
    "symbol": "BLUM_USDT",
    "open_interest": 136155.84,
    "volume_24h": 89954.74336942512
  },
  {
    "symbol": "BEL_USDT",
    "open_interest": 135427.13,
    "volume_24h": 773230.373786493
  },
  {
    "symbol": "FIS_USDT",
    "open_interest": 134994.72,
    "volume_24h": 307451.553029359
  },
  {
    "symbol": "MOVR_USDT",
    "open_interest": 131869.66,
    "volume_24h": 1384567.5759819422
  },
  {
    "symbol": "TAC_USDT",
    "open_interest": 131452.22,
    "volume_24h": 2993352.094206661
  },
  {
    "symbol": "ARK_USDT",
    "open_interest": 130902.91,
    "volume_24h": 1022947.3871001751
  },
  {
    "symbol": "XVS_USDT",
    "open_interest": 130733.07,
    "volume_24h": 687012.3102962712
  },
  {
    "symbol": "ALPINE_USDT",
    "open_interest": 130603.13,
    "volume_24h": 124966.86223323843
  },
  {
    "symbol": "AI_USDT",
    "open_interest": 129250.19,
    "volume_24h": 1778508.1002829166
  },
  {
    "symbol": "SERAPH_USDT",
    "open_interest": 128965.0,
    "volume_24h": 420015.87543146795
  },
  {
    "symbol": "HOOK_USDT",
    "open_interest": 128542.95,
    "volume_24h": 1402430.6703690242
  },
  {
    "symbol": "NKN_USDT",
    "open_interest": 128220.39,
    "volume_24h": 368099.37061384425
  },
  {
    "symbol": "AMZNX_USDT",
    "open_interest": 126770.01,
    "volume_24h": 128620.62970128143
  },
  {
    "symbol": "ORDER_USDT",
    "open_interest": 126060.64,
    "volume_24h": 289765.2295974553
  },
  {
    "symbol": "VELODROME_USDT",
    "open_interest": 126013.22,
    "volume_24h": 368592.2920922714
  },
  {
    "symbol": "CESS_USDT",
    "open_interest": 125364.88,
    "volume_24h": 385046.58809810627
  },
  {
    "symbol": "STORJ_USDT",
    "open_interest": 124806.14,
    "volume_24h": 1006185.750352958
  },
  {
    "symbol": "ZETA_USDT",
    "open_interest": 124701.93,
    "volume_24h": 52279.232536343436
  },
  {
    "symbol": "TNSR_USDT",
    "open_interest": 123083.99,
    "volume_24h": 69800.80952472972
  },
  {
    "symbol": "DARK_USDT",
    "open_interest": 122862.46,
    "volume_24h": 6166493.267181531
  },
  {
    "symbol": "NMR_USDT",
    "open_interest": 122038.08,
    "volume_24h": 1489117.4788457034
  },
  {
    "symbol": "LEVER_USDT",
    "open_interest": 121936.05,
    "volume_24h": 52931.31138454808
  },
  {
    "symbol": "BADGER_USDT",
    "open_interest": 121841.96,
    "volume_24h": 140232.68185018585
  },
  {
    "symbol": "ORCA_USDT",
    "open_interest": 120327.49,
    "volume_24h": 186766.23687782526
  },
  {
    "symbol": "SC_USDT",
    "open_interest": 120293.17,
    "volume_24h": 802425.7792616549
  },
  {
    "symbol": "SCA_USDT",
    "open_interest": 119927.68,
    "volume_24h": 181552.39007580985
  },
  {
    "symbol": "CHEEMS_USDT",
    "open_interest": 119647.94,
    "volume_24h": 233060.06498548365
  },
  {
    "symbol": "ALU_USDT",
    "open_interest": 119532.38,
    "volume_24h": 249435.53752270353
  },
  {
    "symbol": "OGN_USDT",
    "open_interest": 118932.35,
    "volume_24h": 179049.26173661771
  },
  {
    "symbol": "MAV_USDT",
    "open_interest": 117919.16,
    "volume_24h": 1411769.874935281
  },
  {
    "symbol": "RDNT_USDT",
    "open_interest": 116330.71,
    "volume_24h": 102700.18032218015
  },
  {
    "symbol": "SXP_USDT",
    "open_interest": 115954.22,
    "volume_24h": 256047.68953721417
  },
  {
    "symbol": "SFP_USDT",
    "open_interest": 115880.69,
    "volume_24h": 594791.9334197633
  },
  {
    "symbol": "L3_USDT",
    "open_interest": 115031.16,
    "volume_24h": 112384.13143507093
  },
  {
    "symbol": "SKL_USDT",
    "open_interest": 114954.16,
    "volume_24h": 572774.5092228727
  },
  {
    "symbol": "BAIDOGE_USDT",
    "open_interest": 113853.98,
    "volume_24h": 155360.202980809
  },
  {
    "symbol": "CLOUD_USDT",
    "open_interest": 113039.02,
    "volume_24h": 575313.4051027142
  },
  {
    "symbol": "AVA_USDT",
    "open_interest": 112972.93,
    "volume_24h": 550646.5799730342
  },
  {
    "symbol": "HIFI_USDT",
    "open_interest": 112487.04,
    "volume_24h": 1366921.5324311524
  },
  {
    "symbol": "PERP_USDT",
    "open_interest": 111674.19,
    "volume_24h": 397547.12513604923
  },
  {
    "symbol": "MSTRX_USDT",
    "open_interest": 111542.59,
    "volume_24h": 382367.86707646016
  },
  {
    "symbol": "HIVE_USDT",
    "open_interest": 110241.02,
    "volume_24h": 190770.16564073166
  },
  {
    "symbol": "BEAMX_USDT",
    "open_interest": 109585.23,
    "volume_24h": 64917.38530325297
  },
  {
    "symbol": "REI_USDT",
    "open_interest": 109198.06,
    "volume_24h": 216707.522353674
  },
  {
    "symbol": "ARPA_USDT",
    "open_interest": 108927.08,
    "volume_24h": 819370.9051141281
  },
  {
    "symbol": "BICO_USDT",
    "open_interest": 108824.24,
    "volume_24h": 31924.133980840885
  },
  {
    "symbol": "ELDE_USDT",
    "open_interest": 108585.8,
    "volume_24h": 92445.84379214735
  },
  {
    "symbol": "AUDIO_USDT",
    "open_interest": 107413.76,
    "volume_24h": 1402436.1757861653
  },
  {
    "symbol": "DENT_USDT",
    "open_interest": 106394.68,
    "volume_24h": 779976.2952444705
  },
  {
    "symbol": "BID_USDT",
    "open_interest": 106193.8,
    "volume_24h": 424548.3469590947
  },
  {
    "symbol": "MYRIA_USDT",
    "open_interest": 105895.3,
    "volume_24h": 842531.6991577139
  },
  {
    "symbol": "F_USDT",
    "open_interest": 104773.21,
    "volume_24h": 566411.0660512996
  },
  {
    "symbol": "PUNDIX_USDT",
    "open_interest": 104514.86,
    "volume_24h": 172965.51575465366
  },
  {
    "symbol": "OXT_USDT",
    "open_interest": 103687.53,
    "volume_24h": 1461729.7846296465
  },
  {
    "symbol": "STEEM_USDT",
    "open_interest": 102793.46,
    "volume_24h": 1603385.7898334125
  },
  {
    "symbol": "POLYX_USDT",
    "open_interest": 102520.15,
    "volume_24h": 1673437.6335560617
  },
  {
    "symbol": "AVL_USDT",
    "open_interest": 100564.6,
    "volume_24h": 560137.5565222716
  },
  {
    "symbol": "BRIC_USDT",
    "open_interest": 98930.93,
    "volume_24h": 34703.08156583046
  },
  {
    "symbol": "HIGH_USDT",
    "open_interest": 96381.15,
    "volume_24h": 198072.83880538016
  },
  {
    "symbol": "T_USDT",
    "open_interest": 96240.28,
    "volume_24h": 51503.32865141903
  },
  {
    "symbol": "ONT_USDT",
    "open_interest": 95985.99,
    "volume_24h": 62511.547509923534
  },
  {
    "symbol": "DEGO_USDT",
    "open_interest": 95133.63,
    "volume_24h": 119358.00440608125
  },
  {
    "symbol": "LSK_USDT",
    "open_interest": 93027.63,
    "volume_24h": 1000193.3616791385
  },
  {
    "symbol": "WEN_USDT",
    "open_interest": 92059.97,
    "volume_24h": 13264.087998535277
  },
  {
    "symbol": "RLC_USDT",
    "open_interest": 91896.28,
    "volume_24h": 137036.73708738017
  },
  {
    "symbol": "SOLO_USDT",
    "open_interest": 91639.34,
    "volume_24h": 295369.9385227384
  },
  {
    "symbol": "AWE_USDT",
    "open_interest": 90821.39,
    "volume_24h": 1288285.8489801567
  },
  {
    "symbol": "PHB_USDT",
    "open_interest": 89352.27,
    "volume_24h": 978671.8623530422
  },
  {
    "symbol": "TLM_USDT",
    "open_interest": 89294.41,
    "volume_24h": 329483.10160119325
  },
  {
    "symbol": "DUSK_USDT",
    "open_interest": 87204.17,
    "volume_24h": 296837.027783166
  },
  {
    "symbol": "ASTR_USDT",
    "open_interest": 87162.55,
    "volume_24h": 11143.667317855488
  },
  {
    "symbol": "METAX_USDT",
    "open_interest": 87032.22,
    "volume_24h": 124597.2194877271
  },
  {
    "symbol": "ORBS_USDT",
    "open_interest": 86963.92,
    "volume_24h": 720248.0813396386
  },
  {
    "symbol": "SHM_USDT",
    "open_interest": 86222.32,
    "volume_24h": 289818.6099889959
  },
  {
    "symbol": "ANKR_USDT",
    "open_interest": 86070.09,
    "volume_24h": 406993.6323277399
  },
  {
    "symbol": "POWR_USDT",
    "open_interest": 85786.99,
    "volume_24h": 499837.2656286806
  },
  {
    "symbol": "SYS_USDT",
    "open_interest": 85337.86,
    "volume_24h": 493926.9303237575
  },
  {
    "symbol": "IOST_USDT",
    "open_interest": 84802.18,
    "volume_24h": 1273452.2888313348
  },
  {
    "symbol": "NFP_USDT",
    "open_interest": 84274.22,
    "volume_24h": 839216.6732358516
  },
  {
    "symbol": "WAXP_USDT",
    "open_interest": 83845.99,
    "volume_24h": 724541.7731015882
  },
  {
    "symbol": "FLM_USDT",
    "open_interest": 83763.78,
    "volume_24h": 127154.45282049321
  },
  {
    "symbol": "KILO_USDT",
    "open_interest": 83536.22,
    "volume_24h": 116375.28830463279
  },
  {
    "symbol": "VTHO_USDT",
    "open_interest": 81934.08,
    "volume_24h": 87159.28515288689
  },
  {
    "symbol": "GHIBLI_USDT",
    "open_interest": 81766.91,
    "volume_24h": 57455.911647385234
  },
  {
    "symbol": "LUCE_USDT",
    "open_interest": 81568.88,
    "volume_24h": 721381.9717887935
  },
  {
    "symbol": "AGI_USDT",
    "open_interest": 80050.25,
    "volume_24h": 861153.8631398627
  },
  {
    "symbol": "G_USDT",
    "open_interest": 79934.81,
    "volume_24h": 695597.1970489153
  },
  {
    "symbol": "OBT_USDT",
    "open_interest": 79843.31,
    "volume_24h": 20913.933284543495
  },
  {
    "symbol": "ID_USDT",
    "open_interest": 77313.78,
    "volume_24h": 27371.82217025766
  },
  {
    "symbol": "BOND_USDT",
    "open_interest": 75869.1,
    "volume_24h": 34738.69537107257
  },
  {
    "symbol": "DF_USDT",
    "open_interest": 75842.73,
    "volume_24h": 16525.35240330027
  },
  {
    "symbol": "RAD_USDT",
    "open_interest": 75352.78,
    "volume_24h": 60789.80681431848
  },
  {
    "symbol": "GLMR_USDT",
    "open_interest": 74919.4,
    "volume_24h": 55590.6199994016
  },
  {
    "symbol": "PAL_USDT",
    "open_interest": 72489.71,
    "volume_24h": 19018.849575242548
  },
  {
    "symbol": "STMX_USDT",
    "open_interest": 72458.05,
    "volume_24h": 34129.441967175066
  },
  {
    "symbol": "DODO_USDT",
    "open_interest": 71374.12,
    "volume_24h": 153765.3005726604
  },
  {
    "symbol": "BUZZ_USDT",
    "open_interest": 70732.39,
    "volume_24h": 42476.56721090597
  },
  {
    "symbol": "WHY_USDT",
    "open_interest": 69404.68,
    "volume_24h": 40672.208838751605
  },
  {
    "symbol": "SEND_USDT",
    "open_interest": 69298.95,
    "volume_24h": 404195.78611483367
  },
  {
    "symbol": "SPELL_USDT",
    "open_interest": 68886.35,
    "volume_24h": 1165020.4973958216
  },
  {
    "symbol": "A8_USDT",
    "open_interest": 68720.1,
    "volume_24h": 267562.0086308539
  },
  {
    "symbol": "BTT_USDT",
    "open_interest": 68271.73,
    "volume_24h": 20439.7438665573
  },
  {
    "symbol": "NTRN_USDT",
    "open_interest": 67792.46,
    "volume_24h": 604169.6495465958
  },
  {
    "symbol": "NS_USDT",
    "open_interest": 66760.03,
    "volume_24h": 353129.2495656181
  },
  {
    "symbol": "HOODX_USDT",
    "open_interest": 66418.52,
    "volume_24h": 299718.61147772754
  },
  {
    "symbol": "MLN_USDT",
    "open_interest": 65754.22,
    "volume_24h": 68661.3033796528
  },
  {
    "symbol": "SANTOS_USDT",
    "open_interest": 65369.87,
    "volume_24h": 17980.238752887682
  },
  {
    "symbol": "MASA_USDT",
    "open_interest": 64435.16,
    "volume_24h": 302629.81291133945
  },
  {
    "symbol": "J_USDT",
    "open_interest": 63495.39,
    "volume_24h": 91114.19367324373
  },
  {
    "symbol": "RIF_USDT",
    "open_interest": 63480.19,
    "volume_24h": 191299.951749167
  },
  {
    "symbol": "FLY_USDT",
    "open_interest": 62501.78,
    "volume_24h": 71915.6473696915
  },
  {
    "symbol": "QUICK_USDT",
    "open_interest": 61833.9,
    "volume_24h": 556056.1766471361
  },
  {
    "symbol": "SWEAT_USDT",
    "open_interest": 61414.72,
    "volume_24h": 249183.53601876463
  },
  {
    "symbol": "HOT_USDT",
    "open_interest": 59369.51,
    "volume_24h": 885306.8188878938
  },
  {
    "symbol": "MBL_USDT",
    "open_interest": 58196.33,
    "volume_24h": 289941.8806553093
  },
  {
    "symbol": "EDGEN_USDT",
    "open_interest": 57176.93,
    "volume_24h": 19228.23726842284
  },
  {
    "symbol": "D_USDT",
    "open_interest": 56293.2,
    "volume_24h": 41734.26399868049
  },
  {
    "symbol": "NAVX_USDT",
    "open_interest": 54341.59,
    "volume_24h": 126046.90017851736
  },
  {
    "symbol": "CELR_USDT",
    "open_interest": 52724.47,
    "volume_24h": 750412.9293807147
  },
  {
    "symbol": "JOE_USDT",
    "open_interest": 52323.67,
    "volume_24h": 564102.6680815866
  },
  {
    "symbol": "PRAI_USDT",
    "open_interest": 52001.4,
    "volume_24h": 27315.87781871213
  },
  {
    "symbol": "WAXL_USDT",
    "open_interest": 50367.84,
    "volume_24h": 86005.61229825702
  },
  {
    "symbol": "QQQX_USDT",
    "open_interest": 49931.66,
    "volume_24h": 54161.03134211037
  },
  {
    "symbol": "RDO_USDT",
    "open_interest": 49763.62,
    "volume_24h": 421791.957057051
  },
  {
    "symbol": "BOOM_USDT",
    "open_interest": 48149.65,
    "volume_24h": 66093.80505026308
  },
  {
    "symbol": "FORTH_USDT",
    "open_interest": 48134.48,
    "volume_24h": 647182.1214800227
  },
  {
    "symbol": "AAPLX_USDT",
    "open_interest": 48119.99,
    "volume_24h": 18766.661203079722
  },
  {
    "symbol": "REQ_USDT",
    "open_interest": 47450.45,
    "volume_24h": 221854.286698451
  },
  {
    "symbol": "LOOM_USDT",
    "open_interest": 47053.62,
    "volume_24h": 9365.238769277295
  },
  {
    "symbol": "DGB_USDT",
    "open_interest": 46633.49,
    "volume_24h": 193339.49565469337
  },
  {
    "symbol": "COS_USDT",
    "open_interest": 46123.08,
    "volume_24h": 1106469.4540212452
  },
  {
    "symbol": "BOBA_USDT",
    "open_interest": 45348.99,
    "volume_24h": 124138.36096761649
  },
  {
    "symbol": "FDUSD_USDT",
    "open_interest": 45152.05,
    "volume_24h": 7101.699700519646
  },
  {
    "symbol": "BLZ_USDT",
    "open_interest": 45130.23,
    "volume_24h": 37677.50318862027
  },
  {
    "symbol": "SPYX_USDT",
    "open_interest": 45117.44,
    "volume_24h": 187869.9074940545
  },
  {
    "symbol": "STG_USDT",
    "open_interest": 42571.08,
    "volume_24h": 35113.74740140929
  },
  {
    "symbol": "GOOGLX_USDT",
    "open_interest": 41554.72,
    "volume_24h": 188486.19374100704
  },
  {
    "symbol": "CATS_USDT",
    "open_interest": 41017.74,
    "volume_24h": 13828.148210964304
  },
  {
    "symbol": "ONG_USDT",
    "open_interest": 38780.0,
    "volume_24h": 226853.87352764234
  },
  {
    "symbol": "LOT_USDT",
    "open_interest": 35237.67,
    "volume_24h": 50065.46273884308
  },
  {
    "symbol": "XNO_USDT",
    "open_interest": 32722.13,
    "volume_24h": 107524.35048597079
  },
  {
    "symbol": "XEC_USDT",
    "open_interest": 31409.27,
    "volume_24h": 4652.6121722797725
  },
  {
    "symbol": "APU_USDT",
    "open_interest": 22746.61,
    "volume_24h": 14235.232755078549
  },
  {
    "symbol": "MOBILE_USDT",
    "open_interest": 21895.19,
    "volume_24h": 56920.68055776246
  },
  {
    "symbol": "PYR_USDT",
    "open_interest": 17438.09,
    "volume_24h": 10175.504123390952
  },
  {
    "symbol": "AMP_USDT",
    "open_interest": 8316.98,
    "volume_24h": 32181.13384563041
  },
  {
    "symbol": "ALT_USDT",
    "open_interest": 304.68,
    "volume_24h": 263104.1424064317
  }
]